{"numFailedTestSuites":1,"numFailedTests":1,"numPassedTestSuites":0,"numPassedTests":1,"numPendingTestSuites":0,"numPendingTests":0,"numRuntimeErrorTestSuites":0,"numTodoTests":0,"numTotalTestSuites":1,"numTotalTests":2,"openHandles":[],"snapshot":{"added":0,"didUpdate":false,"failure":false,"filesAdded":0,"filesRemoved":0,"filesRemovedList":[],"filesUnmatched":0,"filesUpdated":0,"matched":0,"total":0,"unchecked":0,"uncheckedKeysByFile":[],"unmatched":0,"updated":0},"startTime":1773916883167,"success":false,"testResults":[{"assertionResults":[{"ancestorTitles":["POST /api/contract/provider/updateProvider"],"duration":3,"failing":false,"failureDetails":[{"matcherResult":{"message":"\u001b[2mexpect(\u001b[22m\u001b[31mreceived\u001b[39m\u001b[2m).\u001b[22mtoMatch\u001b[2m(\u001b[22m\u001b[32mexpected\u001b[39m\u001b[2m)\u001b[22m\n\nExpected pattern: \u001b[32m/Must be executed via user wallet signature/\u001b[39m\nReceived string:  \u001b[31m\"Missing required fields: name, email, country, userAddress\"\u001b[39m","pass":false}}],"failureMessages":["Error: \u001b[2mexpect(\u001b[22m\u001b[31mreceived\u001b[39m\u001b[2m).\u001b[22mtoMatch\u001b[2m(\u001b[22m\u001b[32mexpected\u001b[39m\u001b[2m)\u001b[22m\n\nExpected pattern: \u001b[32m/Must be executed via user wallet signature/\u001b[39m\nReceived string:  \u001b[31m\"Missing required fields: name, email, country, userAddress\"\u001b[39m\n    at Object.toMatch (C:\\Users\\denis\\VSProjects\\Marketplace\\src\\app\\api\\contract\\provider\\updateProvider\\__tests__\\route.test.js:35:24)\n    at processTicksAndRejections (node:internal/process/task_queues:103:5)"],"fullName":"POST /api/contract/provider/updateProvider returns 400 with deprecation message","invocations":1,"location":null,"numPassingAsserts":1,"retryReasons":[],"startAt":1773916884002,"status":"failed","title":"returns 400 with deprecation message"},{"ancestorTitles":["POST /api/contract/provider/updateProvider"],"duration":0,"failing":false,"failureDetails":[],"failureMessages":[],"fullName":"POST /api/contract/provider/updateProvider handles auth errors","invocations":1,"location":null,"numPassingAsserts":1,"retryReasons":[],"startAt":1773916884008,"status":"passed","title":"handles auth errors"}],"endTime":1773916884016,"message":"\u001b[1m\u001b[31m  \u001b[1m● \u001b[22m\u001b[1mPOST /api/contract/provider/updateProvider › returns 400 with deprecation message\u001b[39m\u001b[22m\n\n    \u001b[2mexpect(\u001b[22m\u001b[31mreceived\u001b[39m\u001b[2m).\u001b[22mtoMatch\u001b[2m(\u001b[22m\u001b[32mexpected\u001b[39m\u001b[2m)\u001b[22m\n\n    Expected pattern: \u001b[32m/Must be executed via user wallet signature/\u001b[39m\n    Received string:  \u001b[31m\"Missing required fields: name, email, country, userAddress\"\u001b[39m\n\u001b[2m\u001b[22m\n\u001b[2m    \u001b[0m \u001b[90m 33 |\u001b[39m     \u001b[36mconst\u001b[39m data \u001b[33m=\u001b[39m \u001b[36mawait\u001b[39m res\u001b[33m.\u001b[39mjson()\u001b[22m\n\u001b[2m     \u001b[90m 34 |\u001b[39m     expect(res\u001b[33m.\u001b[39mstatus)\u001b[33m.\u001b[39mtoBe(\u001b[35m400\u001b[39m)\u001b[22m\n\u001b[2m    \u001b[31m\u001b[1m>\u001b[22m\u001b[2m\u001b[39m\u001b[90m 35 |\u001b[39m     expect(data\u001b[33m.\u001b[39merror)\u001b[33m.\u001b[39mtoMatch(\u001b[35m/Must be executed via user wallet signature/\u001b[39m)\u001b[22m\n\u001b[2m     \u001b[90m    |\u001b[39m                        \u001b[31m\u001b[1m^\u001b[22m\u001b[2m\u001b[39m\u001b[22m\n\u001b[2m     \u001b[90m 36 |\u001b[39m   })\u001b[22m\n\u001b[2m     \u001b[90m 37 |\u001b[39m\u001b[22m\n\u001b[2m     \u001b[90m 38 |\u001b[39m   it(\u001b[32m'handles auth errors'\u001b[39m\u001b[33m,\u001b[39m \u001b[36masync\u001b[39m () \u001b[33m=>\u001b[39m {\u001b[0m\u001b[22m\n\u001b[2m\u001b[22m\n\u001b[2m      \u001b[2mat Object.toMatch (\u001b[22m\u001b[2m\u001b[0m\u001b[36msrc/app/api/contract/provider/updateProvider/__tests__/route.test.js\u001b[39m\u001b[0m\u001b[2m:35:24)\u001b[22m\u001b[2m\u001b[22m\n","name":"C:\\Users\\denis\\VSProjects\\Marketplace\\src\\app\\api\\contract\\provider\\updateProvider\\__tests__\\route.test.js","startTime":1773916883772,"status":"failed","summary":""}],"wasInterrupted":false}
